data_exchange_agent/__init__.py
data_exchange_agent/__version__.py
data_exchange_agent/configuration_example.toml
data_exchange_agent/container.py
data_exchange_agent/custom_exceptions.py
data_exchange_agent/main.py
data_exchange_agent/config/__init__.py
data_exchange_agent/config/base_config.py
data_exchange_agent/config/cli.py
data_exchange_agent/config/default.py
data_exchange_agent/config/manager.py
data_exchange_agent/config/toml.py
data_exchange_agent/config/sections/__init__.py
data_exchange_agent/config/sections/application.py
data_exchange_agent/config/sections/base_section_config.py
data_exchange_agent/config/sections/server.py
data_exchange_agent/config/sections/connections/__init__.py
data_exchange_agent/config/sections/connections/base.py
data_exchange_agent/config/sections/connections/connection_registry.py
data_exchange_agent/config/sections/connections/cloud_storages/__init__.py
data_exchange_agent/config/sections/connections/cloud_storages/base.py
data_exchange_agent/config/sections/connections/cloud_storages/snowflake/__init__.py
data_exchange_agent/config/sections/connections/cloud_storages/snowflake/authenticator_type.py
data_exchange_agent/config/sections/connections/cloud_storages/snowflake/base.py
data_exchange_agent/config/sections/connections/cloud_storages/snowflake/connection_name.py
data_exchange_agent/config/sections/connections/cloud_storages/snowflake/external_browser.py
data_exchange_agent/config/sections/connections/cloud_storages/snowflake/password.py
data_exchange_agent/config/sections/connections/jdbc/__init__.py
data_exchange_agent/config/sections/connections/jdbc/base.py
data_exchange_agent/config/sections/connections/jdbc/postgresql.py
data_exchange_agent/config/sections/connections/jdbc/sqlserver.py
data_exchange_agent/config/sections/task_sources/__init__.py
data_exchange_agent/config/sections/task_sources/api.py
data_exchange_agent/config/sections/task_sources/snowflake_stored_procedure.py
snowflake_data_exchange_agent-1.1.0.dist-info/METADATA
snowflake_data_exchange_agent-1.1.0.dist-info/WHEEL
snowflake_data_exchange_agent-1.1.0.dist-info/entry_points.txt
snowflake_data_exchange_agent-1.1.0.dist-info/RECORD
