Metadata-Version: 2.4
Name: snowflake-data-exchange-agent
Version: 1.1.0
Summary: Data exchange agent for migrations and validation
Project-URL: Bug Tracker, https://github.com/snowflakedb/migrations-data-validation/issues
Project-URL: Source code, https://github.com/snowflakedb/migrations-data-validation/
Project-URL: homepage, https://www.snowflake.com/
Author-email: "Snowflake, Inc." <snowflake-python-libraries-dl@snowflake.com>
License: Apache License, Version 2.0
Keywords: Snowflake,analytics,cloud,data,data-analysis,data-analytics,data-engineering,data-management,data-processing,data-science,data-visualization,data-warehouse,database
Classifier: Development Status :: 3 - Alpha
Classifier: Environment :: Console
Classifier: Environment :: Other Environment
Classifier: Intended Audience :: Developers
Classifier: Intended Audience :: Education
Classifier: Intended Audience :: Information Technology
Classifier: Intended Audience :: System Administrators
Classifier: License :: OSI Approved :: Apache Software License
Classifier: Operating System :: OS Independent
Classifier: Programming Language :: Python :: 3 :: Only
Classifier: Programming Language :: SQL
Classifier: Topic :: Database
Classifier: Topic :: Scientific/Engineering :: Information Analysis
Classifier: Topic :: Software Development
Classifier: Topic :: Software Development :: Libraries
Classifier: Topic :: Software Development :: Libraries :: Application Frameworks
Classifier: Topic :: Software Development :: Libraries :: Python Modules
Requires-Python: <3.13,>=3.10
Requires-Dist: azure-identity==1.25.0
Requires-Dist: azure-storage-blob==12.26.0
Requires-Dist: boto3==1.40.41
Requires-Dist: dependency-injector==4.48.2
Requires-Dist: flask==3.1.2
Requires-Dist: jaydebeapi==1.2.3
Requires-Dist: psutil==7.1.0
Requires-Dist: psycopg2-binary==2.9.10
Requires-Dist: py4j==0.10.9.9
Requires-Dist: pyarrow==22.0.0
Requires-Dist: requests==2.32.5
Requires-Dist: snowflake-connector-python==4.0.0
Requires-Dist: sqlparse==0.5.4
Requires-Dist: toml==0.10.2
Requires-Dist: urllib3==2.6.0
Requires-Dist: waitress==3.0.2
Provides-Extra: all
Requires-Dist: parameterized>=0.9.0; extra == 'all'
Requires-Dist: pytest-cov>=4.0.0; extra == 'all'
Requires-Dist: pytest-mock>=3.10.0; extra == 'all'
Requires-Dist: pytest>=7.0.0; extra == 'all'
Requires-Dist: ruff>=0.1.0; extra == 'all'
Provides-Extra: development
Requires-Dist: parameterized>=0.9.0; extra == 'development'
Requires-Dist: pytest-cov>=4.0.0; extra == 'development'
Requires-Dist: pytest-mock>=3.10.0; extra == 'development'
Requires-Dist: pytest>=7.0.0; extra == 'development'
Requires-Dist: ruff>=0.1.0; extra == 'development'
